check_pyproject/__init__.py
check_pyproject/__main__.py
check_pyproject/check_pyproject_toml.py
check_pyproject/poetry_requirement.py
check_pyproject/settings.py
check_pyproject/version_utils.py
check_pyproject/clibones/__init__.py
check_pyproject/clibones/application_settings.py
check_pyproject/clibones/config_file.py
check_pyproject/clibones/config_file_base.py
check_pyproject/clibones/info_control.py
check_pyproject/clibones/json_config_file.py
check_pyproject/clibones/logger_control.py
check_pyproject/clibones/toml_config_file.py
check_pyproject-0.1.1.dist-info/METADATA
check_pyproject-0.1.1.dist-info/WHEEL
check_pyproject-0.1.1.dist-info/entry_points.txt
check_pyproject-0.1.1.dist-info/RECORD
