Metadata-Version: 2.3
Name: check_pyproject
Version: 0.1.1
Summary: This tool facilitates syncing of the project and the tool.poetry tables in your pyproject.toml.
Project-URL: check_pyproject, https://github.com/royw/check_pyproject
Author-email: Roy Wright <roy@wright.org>
Maintainer-email: Roy Wright <roy@wright.org>
License: MIT License
Keywords: check,pyproject,python
Classifier: Development Status :: 2 - Pre-Alpha
Classifier: Environment :: Console
Classifier: Intended Audience :: Developers
Classifier: License :: OSI Approved :: MIT License
Classifier: Natural Language :: English
Classifier: Operating System :: POSIX :: Linux
Classifier: Programming Language :: Python :: 3
Requires-Python: >=3.11
Requires-Dist: loguru<0.8.0,>=0.7.2
Requires-Dist: packaging<25.0.0,>=24.0.0
Requires-Dist: pathvalidate<4.0.0,>=3.2.0
Requires-Dist: tomlkit<0.13.0,>=0.12.5
Provides-Extra: dev
Requires-Dist: blacken-docs<2.0.0,>=1.18.0; extra == 'dev'
Requires-Dist: build<2.0.0,>=1.2.1; extra == 'dev'
Requires-Dist: fawltydeps<0.16.0,>=0.15.0; extra == 'dev'
Requires-Dist: flict<2.0.0,>=1.2.14; extra == 'dev'
Requires-Dist: httpx<0.28.0,>=0.27.0; extra == 'dev'
Requires-Dist: liccheck<0.10.0,>=0.9.2; extra == 'dev'
Requires-Dist: mypy<2.0.0,>=1.10.1; extra == 'dev'
Requires-Dist: pip-tools<8.0.0,>=7.4.1; extra == 'dev'
Requires-Dist: pre-commit<4.0.0,>=3.7.1; extra == 'dev'
Requires-Dist: pyupgrade<4.0.0,>=3.16.0; extra == 'dev'
Requires-Dist: reuse<4.0.0,>=3.0.2; extra == 'dev'
Requires-Dist: ruff<0.5.0,>=0.4.7; extra == 'dev'
Requires-Dist: shellcheck-py<0.11.0,>=0.10.0.1; extra == 'dev'
Requires-Dist: toml-cli<0.8.0,>=0.7.0; extra == 'dev'
Requires-Dist: twine<6.0.0,>=5.1.1; extra == 'dev'
Requires-Dist: validate-pyproject<0.19.0,>=0.18.0; extra == 'dev'
Provides-Extra: docs
Requires-Dist: mkdocs-gen-files<0.6.0,>=0.5.0; extra == 'docs'
Requires-Dist: mkdocs-literate-nav<0.7.0,>=0.6.1; extra == 'docs'
Requires-Dist: mkdocs-material<10.0.0,>=9.5.25; extra == 'docs'
Requires-Dist: mkdocs-section-index<0.4.0,>=0.3.9; extra == 'docs'
Requires-Dist: mkdocs<2.0.0,>=1.6.0; extra == 'docs'
Requires-Dist: mkdocstrings-python<2.0.0,>=1.10.3; extra == 'docs'
Requires-Dist: mkdocstrings<0.26.0,>=0.25.1; extra == 'docs'
Provides-Extra: metrics
Requires-Dist: radon<7.0.0,>=6.0.1; extra == 'metrics'
Provides-Extra: sphinx
Requires-Dist: furo<2025.0.0,>=2024.5.6; extra == 'sphinx'
Requires-Dist: myst-parser<4.0.0,>=3.0.1; extra == 'sphinx'
Requires-Dist: sphinx-autodoc-typehints<3.0.0,>=2.1.1; extra == 'sphinx'
Requires-Dist: sphinx-copybutton<0.6.0,>=0.5.2; extra == 'sphinx'
Requires-Dist: sphinx<8.0.0,>=7.3.7; extra == 'sphinx'
Provides-Extra: test
Requires-Dist: coverage[toml]<8.0.0,>=7.5.4; extra == 'test'
Requires-Dist: pytest-cov<6.0.0,>=5.0.0; extra == 'test'
Requires-Dist: pytest-xdist[psutil]<4.0.0,>=3.6.1; extra == 'test'
Requires-Dist: pytest<9.0.0,>=8.2.2; extra == 'test'
Requires-Dist: tox<5.0.0,>=4.14.2; extra == 'test'
